lldblogger/__init__.py
lldblogger/breakpoint_log_loader.py
lldblogger/inject_script.py
lldblogger/runner.py
lldblogger/utils.py
lldblogger_cli-1.0.data/scripts/lldblogger_cli
lldblogger_cli-1.0.dist-info/METADATA
lldblogger_cli-1.0.dist-info/WHEEL
lldblogger_cli-1.0.dist-info/top_level.txt
lldblogger_cli-1.0.dist-info/RECORD
