Metadata-Version: 2.1
Name: lldblogger-cli
Version: 1.0
Summary: __pip_description__
Home-page: UNKNOWN
Author: ocean
Author-email: tomcat1991@126.com
License: MIT
Platform: UNKNOWN
Classifier: Programming Language :: Python :: 3
Classifier: License :: OSI Approved :: MIT License
Classifier: Operating System :: OS Independent
Requires-Dist: coloredlogs
Requires-Dist: fire
